cytomulate/__init__.py
cytomulate/__main__.py
cytomulate/cell_graph_general.py
cytomulate/cell_type_general.py
cytomulate/cytof_data_general.py
cytomulate/utilities.py
cytomulate/creation/__init__.py
cytomulate/creation/cell_graph.py
cytomulate/creation/cell_type.py
cytomulate/creation/cytof_data.py
cytomulate/emulation/__init__.py
cytomulate/emulation/cell_graph.py
cytomulate/emulation/cell_type.py
cytomulate/emulation/cytof_data.py
cytomulate-0.2.0.dist-info/LICENSE.txt
cytomulate-0.2.0.dist-info/METADATA
cytomulate-0.2.0.dist-info/WHEEL
cytomulate-0.2.0.dist-info/top_level.txt
cytomulate-0.2.0.dist-info/RECORD
