Metadata-Version: 2.1
Name: cytomulate
Version: 0.2.0
Summary: Accurate and Efficient Simulation of CyTOF data
Author: Yuqiu Yang, Kevin Wang, Tao Wang, Sherry Wang
Author-email: yuqiuy@smu.edu, kevinwang@smu.edu, Tao.Wang@UTSouthwestern.edu, swang@smu.edu
Classifier: Programming Language :: Python :: 3 :: Only
Classifier: Natural Language :: English
Classifier: Intended Audience :: Science/Research
Requires-Python: >=3.5
License-File: LICENSE.txt
Requires-Dist: numpy
Requires-Dist: scipy
Requires-Dist: scikit-learn
Requires-Dist: networkx
Requires-Dist: matplotlib
Requires-Dist: tqdm
